vram.v
// 64x48 four-bit framebuffer for VGA-style simulation output.
// This is intentionally simulation-friendly rather than synthesis-pure:
// line and rectangle drawing are implemented as tasks for devkit hacking.
module vram(
    input clk,
    input we,
    input [5:0] write_x,
    input [5:0] write_y,
    input [3:0] write_color,
    input [5:0] read_x,
    input [5:0] read_y,
    output [3:0] read_color
);
    localparam W = 64;
    localparam H = 48;
    localparam SIZE = W * H;

    reg [3:0] mem [0:SIZE-1];
    integer i;
    integer dx;
    integer dy;
    integer sx;
    integer sy;
    integer err;
    integer e2;
    integer cx;
    integer cy;

    initial begin
        for (i = 0; i < SIZE; i = i + 1)
            mem[i] = 4'h0;
    end

    always @(posedge clk) begin
        if (we && write_x < W && write_y < H)
            mem[(write_y * W) + write_x] <= write_color;
    end

    assign read_color = (read_x < W && read_y < H) ? mem[(read_y * W) + read_x] : 4'h0;

    task pset;
        input [5:0] x;
        input [5:0] y;
        input [3:0] color;
        begin
            if (x < W && y < H) begin
                mem[(y * W) + x] = color;
                $display("VRAM_PSET x=%0d y=%0d c=%0d", x, y, color);
            end
        end
    endtask

    task clear_all;
        input [3:0] color;
        begin
            for (i = 0; i < SIZE; i = i + 1)
                mem[i] = color;
            $display("VRAM_CLR c=%0d", color);
        end
    endtask

    task draw_line;
        input [5:0] x0;
        input [5:0] y0;
        input [5:0] x1;
        input [5:0] y1;
        input [3:0] color;
        begin
            cx = x0;
            cy = y0;
            dx = (x0 < x1) ? (x1 - x0) : (x0 - x1);
            dy = -((y0 < y1) ? (y1 - y0) : (y0 - y1));
            sx = (x0 < x1) ? 1 : -1;
            sy = (y0 < y1) ? 1 : -1;
            err = dx + dy;

            while (cx != x1 || cy != y1) begin
                pset(cx[5:0], cy[5:0], color);
                e2 = err * 2;
                if (e2 >= dy) begin
                    err = err + dy;
                    cx = cx + sx;
                end
                if (e2 <= dx) begin
                    err = err + dx;
                    cy = cy + sy;
                end
            end
            pset(x1, y1, color);
            $display("VRAM_LINE x0=%0d y0=%0d x1=%0d y1=%0d c=%0d", x0, y0, x1, y1, color);
        end
    endtask

    task draw_rect;
        input [5:0] x;
        input [5:0] y;
        input [5:0] w;
        input [5:0] h;
        input [3:0] color;
        begin
            if (w == 0 || h == 0) begin
                pset(x, y, color);
            end else begin
                draw_line(x, y, x + w - 1, y, color);
                draw_line(x, y + h - 1, x + w - 1, y + h - 1, color);
                draw_line(x, y, x, y + h - 1, color);
                draw_line(x + w - 1, y, x + w - 1, y + h - 1, color);
            end
            $display("VRAM_RECT x=%0d y=%0d w=%0d h=%0d c=%0d", x, y, w, h, color);
        end
    endtask

    task dump_nonzero;
        integer px;
        integer py;
        begin
            for (py = 0; py < H; py = py + 1) begin
                for (px = 0; px < W; px = px + 1) begin
                    if (mem[(py * W) + px] != 4'h0)
                        $display("FB %0d %0d %0d", px, py, mem[(py * W) + px]);
                end
            end
        end
    endtask
endmodule

control.v
// Minimal run/halt control for the Z+ core.
// The CPU owns the micro-state; this unit latches the architectural halt bit.
module control(
    input clk,
    input reset,
    input halt_req,
    output reg halt_flag,
    output running
);
    always @(posedge clk) begin
        if (reset)
            halt_flag <= 1'b0;
        else if (halt_req)
            halt_flag <= 1'b1;
    end

    assign running = !halt_flag;
endmodule

alu.v
// Z21 ALU for the Z+ 12-bit fantasy CPU.
// Operations wrap to 12 bits, matching the small-machine feel.
module alu(
    input  [3:0]  op,
    input  [11:0] a,
    input  [11:0] b,
    output reg [11:0] y,
    output reg carry,
    output zero,
    output neg
);
    reg [12:0] wide;

    always @* begin
        y = 12'h000;
        carry = 1'b0;
        wide = 13'h0000;

        case (op)
            4'h3: begin
                wide = {1'b0, a} + {1'b0, b};
                y = wide[11:0];
                carry = wide[12];
            end
            4'h4: begin
                wide = {1'b0, a} - {1'b0, b};
                y = wide[11:0];
                carry = wide[12];
            end
            4'h5: y = (a * b) & 12'hfff;
            4'h6: y = (b == 12'h000) ? 12'hfff : (a / b);
            4'h7: y = a & b;
            4'h8: y = a | b;
            4'h9: y = a ^ b;
            default: y = a;
        endcase
    end

    assign zero = (y == 12'h000);
    assign neg = y[11];
endmodule

regs.v
// Eight 12-bit registers, R0 through R7.
// Three async read ports let video instructions sample x, y, and color.
module regs(
    input clk,
    input reset,
    input we,
    input [2:0] waddr,
    input [11:0] wdata,
    input [2:0] raddr_a,
    input [2:0] raddr_b,
    input [2:0] raddr_c,
    output [11:0] rdata_a,
    output [11:0] rdata_b,
    output [11:0] rdata_c,
    output [11:0] r0,
    output [11:0] r1,
    output [11:0] r2,
    output [11:0] r3,
    output [11:0] r4,
    output [11:0] r5,
    output [11:0] r6,
    output [11:0] r7
);
    reg [11:0] bank [0:7];
    integer i;

    always @(posedge clk) begin
        if (reset) begin
            for (i = 0; i < 8; i = i + 1)
                bank[i] <= 12'h000;
        end else if (we) begin
            bank[waddr] <= wdata & 12'hfff;
        end
    end

    assign rdata_a = bank[raddr_a];
    assign rdata_b = bank[raddr_b];
    assign rdata_c = bank[raddr_c];

    assign r0 = bank[0];
    assign r1 = bank[1];
    assign r2 = bank[2];
    assign r3 = bank[3];
    assign r4 = bank[4];
    assign r5 = bank[5];
    assign r6 = bank[6];
    assign r7 = bank[7];
endmodule

decode.v
// Z+ instruction decoder.
// All instruction words are 12 bits. Some opcodes consume a following
// 12-bit literal or register descriptor word.
module decode(
    input  [11:0] instr,
    output [3:0]  opcode,
    output [7:0]  sysop,
    output [2:0]  rd,
    output [2:0]  rs,
    output [1:0]  subop,
    output [2:0]  grp_a,
    output [2:0]  grp_b
);
    assign opcode = instr[11:8];
    assign sysop  = instr[7:0];
    assign rd     = instr[7:5];
    assign rs     = instr[4:2];
    assign subop  = instr[7:6];
    assign grp_a  = instr[5:3];
    assign grp_b  = instr[2:0];
endmodule

z21.v
// Z21: an experimental Z+ 12-bit fantasy CPU.
// Retro console devkit rules:
// - 8 general registers, R0-R7
// - 8-bit program counter over 256 words of embedded ROM
// - zero/carry/negative flags
// - small scratch RAM for future experiments
// - 64x48 4-bit VRAM framebuffer
module z21(
    input clk,
    input reset,
    output halted,
    output video_dirty,
    output [7:0] pc_dbg,
    output [2:0] flags_dbg,
    output [11:0] r0_dbg,
    output [11:0] r1_dbg,
    output [11:0] r2_dbg,
    output [11:0] r3_dbg,
    output [11:0] r4_dbg,
    output [11:0] r5_dbg,
    output [11:0] r6_dbg,
    output [11:0] r7_dbg
);
    localparam S_FETCH = 3'd0;
    localparam S_EXEC  = 3'd1;
    localparam S_VIDEO = 3'd2;

    reg [11:0] rom [0:255];
    reg [11:0] ram [0:31];
    reg [7:0] pc;
    reg [11:0] instr;
    reg [2:0] state;
    reg [2:0] video_kind;
    reg [5:0] video_x0;
    reg [5:0] video_y0;
    reg [2:0] flags;
    reg [31:0] cycles;
    reg video_dirty_reg;

    reg reg_we;
    reg [2:0] reg_waddr;
    reg [11:0] reg_wdata;
    reg [2:0] read_a;
    reg [2:0] read_b;
    reg [2:0] read_c;

    wire running;
    wire [3:0] opcode;
    wire [7:0] sysop;
    wire [2:0] rd;
    wire [2:0] rs;
    wire [1:0] subop;
    wire [2:0] grp_a;
    wire [2:0] grp_b;

    wire [11:0] ra;
    wire [11:0] rb;
    wire [11:0] rc;
    wire [11:0] alu_y;
    wire alu_carry;
    wire alu_zero;
    wire alu_neg;
    wire halt_decode;

    integer i;

    initial begin
        for (i = 0; i < 256; i = i + 1)
            rom[i] = 12'h000;
        for (i = 0; i < 32; i = i + 1)
            ram[i] = 12'h000;
        pc = 8'h00;
        instr = 12'h000;
        state = S_FETCH;
        video_kind = 3'd0;
        video_x0 = 6'd0;
        video_y0 = 6'd0;
        flags = 3'b000;
        cycles = 0;
        video_dirty_reg = 1'b0;
    end

    decode decoder(
        .instr(instr),
        .opcode(opcode),
        .sysop(sysop),
        .rd(rd),
        .rs(rs),
        .subop(subop),
        .grp_a(grp_a),
        .grp_b(grp_b)
    );

    regs regfile(
        .clk(clk),
        .reset(reset),
        .we(reg_we),
        .waddr(reg_waddr),
        .wdata(reg_wdata),
        .raddr_a(read_a),
        .raddr_b(read_b),
        .raddr_c(read_c),
        .rdata_a(ra),
        .rdata_b(rb),
        .rdata_c(rc),
        .r0(r0_dbg),
        .r1(r1_dbg),
        .r2(r2_dbg),
        .r3(r3_dbg),
        .r4(r4_dbg),
        .r5(r5_dbg),
        .r6(r6_dbg),
        .r7(r7_dbg)
    );

    alu core_alu(
        .op(opcode),
        .a(ra),
        .b(rb),
        .y(alu_y),
        .carry(alu_carry),
        .zero(alu_zero),
        .neg(alu_neg)
    );

    control ctl(
        .clk(clk),
        .reset(reset),
        .halt_req(halt_decode),
        .halt_flag(halted),
        .running(running)
    );

    vram video(
        .clk(clk),
        .we(1'b0),
        .write_x(6'd0),
        .write_y(6'd0),
        .write_color(4'd0),
        .read_x(6'd0),
        .read_y(6'd0),
        .read_color()
    );

    always @* begin
        read_a = rd;
        read_b = rs;
        read_c = 3'd0;
        reg_we = 1'b0;
        reg_waddr = rd;
        reg_wdata = 12'h000;

        if (state == S_EXEC) begin
            case (opcode)
                4'h1: begin
                    reg_we = 1'b1;
                    reg_waddr = rd;
                    reg_wdata = rom[pc];
                end
                4'h2: begin
                    reg_we = 1'b1;
                    reg_waddr = rd;
                    reg_wdata = rb;
                end
                4'h3, 4'h4, 4'h5, 4'h6, 4'h7, 4'h8, 4'h9: begin
                    reg_we = 1'b1;
                    reg_waddr = rd;
                    reg_wdata = alu_y;
                end
                4'ha: begin
                    read_a = grp_a;
                    read_b = grp_b;
                    reg_waddr = grp_a;
                    if (subop == 2'b00) begin
                        reg_we = 1'b1;
                        reg_wdata = ra + 12'h001;
                    end else if (subop == 2'b01) begin
                        reg_we = 1'b1;
                        reg_wdata = ra - 12'h001;
                    end
                end
                4'he: begin
                    read_a = grp_a;
                    read_b = grp_b;
                    if (subop == 2'b11)
                        read_c = grp_a;
                end
                default: begin
                end
            endcase
        end else if (state == S_VIDEO) begin
            read_a = instr[5:3];
            read_b = instr[2:0];
            read_c = rom[pc][5:3];
            if (video_kind == 3'd0)
                read_c = rom[pc][2:0];
            else begin
                read_a = rom[pc][11:9];
                read_b = rom[pc][8:6];
                read_c = rom[pc][5:3];
            end
        end
    end

    always @(posedge clk) begin
        if (reset) begin
            pc <= 8'h00;
            instr <= 12'h000;
            state <= S_FETCH;
            video_kind <= 3'd0;
            video_x0 <= 6'd0;
            video_y0 <= 6'd0;
            flags <= 3'b000;
            cycles <= 0;
            video_dirty_reg <= 1'b0;
        end else if (running) begin
            cycles <= cycles + 1;
            video_dirty_reg <= 1'b0;

            case (state)
                S_FETCH: begin
                    instr <= rom[pc];
                    pc <= pc + 8'd1;
                    state <= S_EXEC;
                end
                S_EXEC: begin
                    case (opcode)
                        4'h0: begin
                            if (sysop == 8'h01) begin
                            end
                        end
                        4'h1: begin
                            pc <= pc + 8'd1;
                            flags[0] <= (rom[pc] == 12'h000);
                            flags[1] <= 1'b0;
                            flags[2] <= rom[pc][11];
                        end
                        4'h2: begin
                            flags[0] <= (rb == 12'h000);
                            flags[1] <= 1'b0;
                            flags[2] <= rb[11];
                        end
                        4'h3, 4'h4, 4'h5, 4'h6, 4'h7, 4'h8, 4'h9: begin
                            flags[0] <= alu_zero;
                            flags[1] <= alu_carry;
                            flags[2] <= alu_neg;
                        end
                        4'ha: begin
                            if (subop == 2'b00) begin
                                flags[0] <= ((ra + 12'h001) == 12'h000);
                                flags[1] <= (ra == 12'hfff);
                                flags[2] <= ((ra + 12'h001) & 12'h800) != 12'h000;
                            end else if (subop == 2'b01) begin
                                flags[0] <= ((ra - 12'h001) == 12'h000);
                                flags[1] <= (ra == 12'h000);
                                flags[2] <= ((ra - 12'h001) & 12'h800) != 12'h000;
                            end else if (subop == 2'b10) begin
                                flags[0] <= (ra == rb);
                                flags[1] <= (ra < rb);
                                flags[2] <= ((ra - rb) & 12'h800) != 12'h000;
                            end
                        end
                        4'hb: pc <= rom[pc][7:0];
                        4'hc: begin
                            if (flags[0])
                                pc <= rom[pc][7:0];
                            else
                                pc <= pc + 8'd1;
                        end
                        4'hd: begin
                            if (!flags[0])
                                pc <= rom[pc][7:0];
                            else
                                pc <= pc + 8'd1;
                        end
                        4'he: begin
                            if (subop == 2'b11) begin
                                video.clear_all(ra[3:0]);
                                video_dirty_reg <= 1'b1;
                            end else begin
                                video_x0 <= ra[5:0];
                                video_y0 <= rb[5:0];
                                video_kind <= {1'b0, subop};
                                state <= S_VIDEO;
                            end
                        end
                        default: begin
                        end
                    endcase

                    if (opcode != 4'he || subop == 2'b11)
                        state <= S_FETCH;
                end
                S_VIDEO: begin
                    if (video_kind == 3'd0)
                        video.pset(video_x0, video_y0, rc[3:0]);
                    else if (video_kind == 3'd1)
                        video.draw_line(video_x0, video_y0, ra[5:0], rb[5:0], rc[3:0]);
                    else if (video_kind == 3'd2)
                        video.draw_rect(video_x0, video_y0, ra[5:0], rb[5:0], rc[3:0]);

                    video_dirty_reg <= 1'b1;
                    pc <= pc + 8'd1;
                    state <= S_FETCH;
                end
                default: state <= S_FETCH;
            endcase
        end
    end

    assign pc_dbg = pc;
    assign flags_dbg = flags;
    assign video_dirty = video_dirty_reg;
    assign halt_decode = (state == S_EXEC && opcode == 4'h0 && sysop == 8'h01);

    task dump_state;
        begin
            $display("STATE cycle=%0d pc=%0d halted=%0d z=%0d c=%0d n=%0d r0=%0d r1=%0d r2=%0d r3=%0d r4=%0d r5=%0d r6=%0d r7=%0d",
                cycles, pc, halted, flags[0], flags[1], flags[2],
                r0_dbg, r1_dbg, r2_dbg, r3_dbg, r4_dbg, r5_dbg, r6_dbg, r7_dbg);
        end
    endtask
endmodule

tbch.v
// Generated Z21 simulation testbench. Regenerate with zasm.py.
module tbch;
    reg clk = 1'b0;
    reg reset = 1'b1;
    wire halted;
    wire video_dirty;
    wire [7:0] pc_dbg;
    wire [2:0] flags_dbg;
    wire [11:0] r0_dbg;
    wire [11:0] r1_dbg;
    wire [11:0] r2_dbg;
    wire [11:0] r3_dbg;
    wire [11:0] r4_dbg;
    wire [11:0] r5_dbg;
    wire [11:0] r6_dbg;
    wire [11:0] r7_dbg;

    integer max_cycles;
    integer live_mode;
    integer frame_stride;
    integer frame_count;
    integer step_i;

    z21 dut(
        .clk(clk),
        .reset(reset),
        .halted(halted),
        .video_dirty(video_dirty),
        .pc_dbg(pc_dbg),
        .flags_dbg(flags_dbg),
        .r0_dbg(r0_dbg),
        .r1_dbg(r1_dbg),
        .r2_dbg(r2_dbg),
        .r3_dbg(r3_dbg),
        .r4_dbg(r4_dbg),
        .r5_dbg(r5_dbg),
        .r6_dbg(r6_dbg),
        .r7_dbg(r7_dbg)
    );

    always #5 clk = ~clk;

    initial begin
        $dumpfile("wave.vcd");
        $dumpvars(0, tbch);
        max_cycles = 512;
        if (!$value$plusargs("cycles=%d", max_cycles))
            max_cycles = 512;
        live_mode = 0;
        if (!$value$plusargs("live=%d", live_mode))
            live_mode = 0;
        frame_stride = 1;
        if (!$value$plusargs("frame_stride=%d", frame_stride))
            frame_stride = 1;
        frame_count = 0;

        dut.rom[0] = 12'h100;
        dut.rom[1] = 12'h000;
        dut.rom[2] = 12'h120;
        dut.rom[3] = 12'h014;
        dut.rom[4] = 12'h140;
        dut.rom[5] = 12'h00f;
        dut.rom[6] = 12'h1a0;
        dut.rom[7] = 12'h000;
        dut.rom[8] = 12'h1c0;
        dut.rom[9] = 12'h001;
        dut.rom[10] = 12'h1e0;
        dut.rom[11] = 12'h040;
        dut.rom[12] = 12'hee8;
        dut.rom[13] = 12'he01;
        dut.rom[14] = 12'h002;
        dut.rom[15] = 12'h318;
        dut.rom[16] = 12'ha87;
        dut.rom[17] = 12'hd00;
        dut.rom[18] = 12'h00c;
        dut.rom[19] = 12'h001;

        #20 reset = 1'b0;
        for (step_i = 0; step_i < max_cycles; step_i = step_i + 1) begin
            @(negedge clk);
            dut.dump_state();
            if (live_mode && video_dirty) begin
                frame_count = frame_count + 1;
                if ((frame_count % frame_stride) == 0) begin
                    $display("FRAME_BEGIN id=%0d cycle=%0d pc=%0d live=1", frame_count, step_i, pc_dbg);
                    dut.video.dump_nonzero();
                    $display("FRAME_END id=%0d", frame_count);
                end
            end
            if (halted)
                step_i = max_cycles;
        end

        $display("FRAME_BEGIN id=%0d cycle=%0d pc=%0d live=0", frame_count + 1, step_i, pc_dbg);
        dut.video.dump_nonzero();
        $display("FRAME_END id=%0d", frame_count + 1);
        dut.dump_state();
        #1 $finish;
    end
endmodule

wave.vcd
$date
	Thu May  7 14:39:13 2026
$end
$version
	Icarus Verilog
$end
$timescale
	1s
$end
$scope module tbch $end
$var wire 1 ! video_dirty $end
$var wire 12 " r7_dbg [11:0] $end
$var wire 12 # r6_dbg [11:0] $end
$var wire 12 $ r5_dbg [11:0] $end
$var wire 12 % r4_dbg [11:0] $end
$var wire 12 & r3_dbg [11:0] $end
$var wire 12 ' r2_dbg [11:0] $end
$var wire 12 ( r1_dbg [11:0] $end
$var wire 12 ) r0_dbg [11:0] $end
$var wire 8 * pc_dbg [7:0] $end
$var wire 1 + halted $end
$var wire 3 , flags_dbg [2:0] $end
$var reg 1 - clk $end
$var reg 1 . reset $end
$var integer 32 / frame_count [31:0] $end
$var integer 32 0 frame_stride [31:0] $end
$var integer 32 1 live_mode [31:0] $end
$var integer 32 2 max_cycles [31:0] $end
$var integer 32 3 step_i [31:0] $end
$scope module dut $end
$var wire 1 - clk $end
$var wire 3 4 flags_dbg [2:0] $end
$var wire 1 5 halt_decode $end
$var wire 8 6 pc_dbg [7:0] $end
$var wire 1 . reset $end
$var wire 1 ! video_dirty $end
$var wire 8 7 sysop [7:0] $end
$var wire 2 8 subop [1:0] $end
$var wire 1 9 running $end
$var wire 3 : rs [2:0] $end
$var wire 3 ; rd [2:0] $end
$var wire 12 < rc [11:0] $end
$var wire 12 = rb [11:0] $end
$var wire 12 > ra [11:0] $end
$var wire 12 ? r7_dbg [11:0] $end
$var wire 12 @ r6_dbg [11:0] $end
$var wire 12 A r5_dbg [11:0] $end
$var wire 12 B r4_dbg [11:0] $end
$var wire 12 C r3_dbg [11:0] $end
$var wire 12 D r2_dbg [11:0] $end
$var wire 12 E r1_dbg [11:0] $end
$var wire 12 F r0_dbg [11:0] $end
$var wire 4 G opcode [3:0] $end
$var wire 1 + halted $end
$var wire 3 H grp_b [2:0] $end
$var wire 3 I grp_a [2:0] $end
$var wire 1 J alu_zero $end
$var wire 12 K alu_y [11:0] $end
$var wire 1 L alu_neg $end
$var wire 1 M alu_carry $end
$var parameter 3 N S_EXEC $end
$var parameter 3 O S_FETCH $end
$var parameter 3 P S_VIDEO $end
$var reg 32 Q cycles [31:0] $end
$var reg 3 R flags [2:0] $end
$var reg 12 S instr [11:0] $end
$var reg 8 T pc [7:0] $end
$var reg 3 U read_a [2:0] $end
$var reg 3 V read_b [2:0] $end
$var reg 3 W read_c [2:0] $end
$var reg 3 X reg_waddr [2:0] $end
$var reg 12 Y reg_wdata [11:0] $end
$var reg 1 Z reg_we $end
$var reg 3 [ state [2:0] $end
$var reg 1 \ video_dirty_reg $end
$var reg 3 ] video_kind [2:0] $end
$var reg 6 ^ video_x0 [5:0] $end
$var reg 6 _ video_y0 [5:0] $end
$var integer 32 ` i [31:0] $end
$scope module core_alu $end
$var wire 1 J zero $end
$var wire 4 a op [3:0] $end
$var wire 1 L neg $end
$var wire 12 b b [11:0] $end
$var wire 12 c a [11:0] $end
$var reg 1 M carry $end
$var reg 13 d wide [12:0] $end
$var reg 12 e y [11:0] $end
$upscope $end
$scope module ctl $end
$var wire 1 - clk $end
$var wire 1 5 halt_req $end
$var wire 1 . reset $end
$var wire 1 9 running $end
$var reg 1 + halt_flag $end
$upscope $end
$scope module decoder $end
$var wire 12 f instr [11:0] $end
$var wire 8 g sysop [7:0] $end
$var wire 2 h subop [1:0] $end
$var wire 3 i rs [2:0] $end
$var wire 3 j rd [2:0] $end
$var wire 4 k opcode [3:0] $end
$var wire 3 l grp_b [2:0] $end
$var wire 3 m grp_a [2:0] $end
$upscope $end
$scope module regfile $end
$var wire 1 - clk $end
$var wire 12 n r0 [11:0] $end
$var wire 12 o r1 [11:0] $end
$var wire 12 p r2 [11:0] $end
$var wire 12 q r3 [11:0] $end
$var wire 12 r r4 [11:0] $end
$var wire 12 s r5 [11:0] $end
$var wire 12 t r6 [11:0] $end
$var wire 12 u r7 [11:0] $end
$var wire 3 v raddr_a [2:0] $end
$var wire 3 w raddr_b [2:0] $end
$var wire 3 x raddr_c [2:0] $end
$var wire 12 y rdata_a [11:0] $end
$var wire 12 z rdata_b [11:0] $end
$var wire 12 { rdata_c [11:0] $end
$var wire 1 . reset $end
$var wire 3 | waddr [2:0] $end
$var wire 12 } wdata [11:0] $end
$var wire 1 Z we $end
$var integer 32 ~ i [31:0] $end
$upscope $end
$scope module video $end
$var wire 1 - clk $end
$var wire 6 !" read_x [5:0] $end
$var wire 6 "" read_y [5:0] $end
$var wire 1 #" we $end
$var wire 4 $" write_color [3:0] $end
$var wire 6 %" write_x [5:0] $end
$var wire 6 &" write_y [5:0] $end
$var wire 4 '" read_color [3:0] $end
$var parameter 32 (" H $end
$var parameter 64 )" SIZE $end
$var parameter 32 *" W $end
$var integer 32 +" cx [31:0] $end
$var integer 32 ," cy [31:0] $end
$var integer 32 -" dx [31:0] $end
$var integer 32 ." dy [31:0] $end
$var integer 32 /" e2 [31:0] $end
$var integer 32 0" err [31:0] $end
$var integer 32 1" i [31:0] $end
$var integer 32 2" sx [31:0] $end
$var integer 32 3" sy [31:0] $end
$scope task clear_all $end
$var reg 4 4" color [3:0] $end
$upscope $end
$scope task draw_line $end
$var reg 4 5" color [3:0] $end
$var reg 6 6" x0 [5:0] $end
$var reg 6 7" x1 [5:0] $end
$var reg 6 8" y0 [5:0] $end
$var reg 6 9" y1 [5:0] $end
$upscope $end
$scope task draw_rect $end
$var reg 4 :" color [3:0] $end
$var reg 6 ;" h [5:0] $end
$var reg 6 <" w [5:0] $end
$var reg 6 =" x [5:0] $end
$var reg 6 >" y [5:0] $end
$upscope $end
$scope task dump_nonzero $end
$var integer 32 ?" px [31:0] $end
$var integer 32 @" py [31:0] $end
$upscope $end
$scope task pset $end
$var reg 4 A" color [3:0] $end
$var reg 6 B" x [5:0] $end
$var reg 6 C" y [5:0] $end
$upscope $end
$upscope $end
$scope task dump_state $end
$upscope $end
$upscope $end
$upscope $end
$enddefinitions $end
$comment Show the parameter values. $end
$dumpall
b1000000 *"
b110000000000 )"
b110000 ("
b10 P
b0 O
b1 N
$end
#0
$dumpvars
bx C"
bx B"
bx A"
bx @"
bx ?"
bx >"
bx ="
bx <"
bx ;"
bx :"
bx 9"
bx 8"
bx 7"
bx 6"
bx 5"
bx 4"
bx 3"
bx 2"
b110000000000 1"
bx 0"
bx /"
bx ."
bx -"
bx ,"
bx +"
b0 '"
b0 &"
b0 %"
b0 $"
0#"
b0 ""
b0 !"
bx ~
b0 }
b0 |
bx {
bx z
bx y
b0 x
b0 w
b0 v
bx u
bx t
bx s
bx r
bx q
bx p
bx o
bx n
b0 m
b0 l
b0 k
b0 j
b0 i
b0 h
b0 g
b0 f
bx e
b0 d
bx c
bx b
b0 a
b100000 `
b0 _
b0 ^
b0 ]
0\
b0 [
0Z
b0 Y
b0 X
b0 W
b0 V
b0 U
b0 T
b0 S
b0 R
b0 Q
0M
xL
bx K
xJ
b0 I
b0 H
b0 G
bx F
bx E
bx D
bx C
bx B
bx A
bx @
bx ?
bx >
bx =
bx <
b0 ;
b0 :
x9
b0 8
b0 7
b0 6
05
b0 4
bx 3
b100000000000 2
b1 1
b1 0
b0 /
1.
0-
b0 ,
x+
b0 *
bx )
bx (
bx '
bx &
bx %
bx $
bx #
bx "
0!
$end
#5
0L
1J
b0 K
b0 e
b0 "
b0 ?
b0 u
b0 #
b0 @
b0 t
b0 $
b0 A
b0 s
b0 %
b0 B
b0 r
b0 &
b0 C
b0 q
b0 '
b0 D
b0 p
b0 (
b0 E
b0 o
b0 >
b0 c
b0 y
b0 =
b0 b
b0 z
b0 <
b0 {
b0 )
b0 F
b0 n
19
0+
b1000 ~
1-
#10
0-
#15
b1000 ~
1-
#20
0-
b1 3
0.
#25
1Z
b1 G
b1 a
b1 k
b1 [
b1 *
b1 6
b1 T
b100000000 S
b100000000 f
b1 Q
1-
#30
b10 3
0-
#35
0Z
b0 [
b1 ,
b1 4
b1 R
b10 *
b10 6
b10 T
b10 Q
1-
#40
b11 3
0-
#45
b1 X
b1 |
b1 U
b1 v
b100000 7
b100000 g
b1 ;
b1 j
b100 I
b100 m
b10100 Y
b10100 }
1Z
b1 [
b11 *
b11 6
b11 T
b100100000 S
b100100000 f
b11 Q
1-
#50
b100 3
0-
#55
b0 Y
b0 }
0Z
0J
b10100 K
b10100 e
b0 [
b0 ,
b0 4
b0 R
b100 *
b100 6
b100 T
b100 Q
b10100 >
b10100 c
b10100 y
b10100 (
b10100 E
b10100 o
1-
#60
b101 3
0-
#65
1J
b0 K
b0 e
b0 >
b0 c
b0 y
b10 X
b10 |
b10 U
b10 v
b1000000 7
b1000000 g
b10 ;
b10 j
b1 8
b1 h
b0 I
b0 m
b1111 Y
b1111 }
1Z
b1 [
b101 *
b101 6
b101 T
b101000000 S
b101000000 f
b101 Q
1-
#70
b110 3
0-
#75
b0 Y
b0 }
0Z
0J
b1111 K
b1111 e
b0 [
b110 *
b110 6
b110 T
b110 Q
b1111 >
b1111 c
b1111 y
b1111 '
b1111 D
b1111 p
1-
#80
b111 3
0-
#85
1J
b0 K
b0 e
b0 >
b0 c
b0 y
b101 X
b101 |
b101 U
b101 v
b10100000 7
b10100000 g
b101 ;
b101 j
b10 8
b10 h
b100 I
b100 m
1Z
b1 [
b111 *
b111 6
b111 T
b110100000 S
b110100000 f
b111 Q
1-
#90
b1000 3
0-
#95
0Z
b0 [
b1 ,
b1 4
b1 R
b1000 *
b1000 6
b1000 T
b1000 Q
1-
#100
b1001 3
0-
#105
b110 X
b110 |
b110 U
b110 v
b11000000 7
b11000000 g
b110 ;
b110 j
b11 8
b11 h
b0 I
b0 m
b1 Y
b1 }
1Z
b1 [
b1001 *
b1001 6
b1001 T
b111000000 S
b111000000 f
b1001 Q
1-
#110
b1010 3
0-
#115
b0 Y
b0 }
0Z
0J
b1 K
b1 e
b0 [
b0 ,
b0 4
b0 R
b1010 *
b1010 6
b1010 T
b1010 Q
b1 >
b1 c
b1 y
b1 #
b1 @
b1 t
1-
#120
b1011 3
0-
#125
1J
b0 K
b0 e
b0 >
b0 c
b0 y
b111 X
b111 |
b111 U
b111 v
b11100000 7
b11100000 g
b111 ;
b111 j
b100 I
b100 m
b1000000 Y
b1000000 }
1Z
b1 [
b1011 *
b1011 6
b1011 T
b111100000 S
b111100000 f
b1011 Q
1-
#130
b1100 3
0-
#135
b0 Y
b0 }
0Z
0J
b1000000 K
b1000000 e
b0 [
b1100 *
b1100 6
b1100 T
b1100 Q
b1000000 >
b1000000 c
b1000000 y
b1000000 "
b1000000 ?
b1000000 u
1-
#140
b1101 3
0-
#145
b0 >
b0 c
b0 y
1J
b0 K
b0 e
b101 W
b101 x
b101 U
b101 v
b0 V
b0 w
b1110 G
b1110 a
b1110 k
b11101000 7
b11101000 g
b10 :
b10 i
b101 I
b101 m
b0 Y
b0 }
0Z
b1 [
b1101 *
b1101 6
b1101 T
b111011101000 S
b111011101000 f
b1101 Q
1-
#150
b1110 3
0-
#155
0J
b1000000 K
b1000000 e
b1111 =
b1111 b
b1111 z
b1000000 >
b1000000 c
b1000000 y
b0 W
b0 x
b10 V
b10 w
b111 U
b111 v
b0 [
1!
1\
b1110 Q
b110000000000 1"
b0 4"
1-
#160
b1111 3
b1000000 ?"
b110000 @"
b1 /
0-
#165
1J
b0 K
b0 e
b0 X
b0 |
b10100 =
b10100 b
b10100 z
b0 >
b0 c
b0 y
b1 7
b1 g
b0 ;
b0 j
b0 :
b0 i
b0 8
b0 h
b0 I
b0 m
b1 H
b1 l
b0 W
b0 x
b1 V
b1 w
b0 U
b0 v
b1 [
b1110 *
b1110 6
b1110 T
b111000000001 S
b111000000001 f
0!
0\
b1111 Q
1-
#170
b10000 3
0-
#175
b1111 <
b1111 {
b10 W
b10 x
b1 V
b1 w
b10 [
b10100 _
b10000 Q
1-
#180
b10001 3
0-
#185
b0 <
b0 {
b0 =
b0 b
b0 z
b0 W
b0 x
b0 V
b0 w
b0 [
b1111 *
b1111 6
b1111 T
1!
1\
b10001 Q
b1111 A"
b10100 C"
b0 B"
1-
#190
b10010 3
b1000000 ?"
b110000 @"
b10 /
0-
#195
b1 Y
b1 }
0J
b1 K
b1 e
b1 d
1Z
b1 =
b1 b
b1 z
b11 G
b11 a
b11 k
b11000 7
b11000 g
b110 :
b110 i
b11 I
b11 m
b0 H
b0 l
b110 V
b110 w
b1 [
b10000 *
b10000 6
b10000 T
b1100011000 S
b1100011000 f
0!
0\
b10010 Q
1-
#200
b10011 3
0-
#205
b0 Y
b0 }
0Z
b10 d
0J
b10 K
b10 e
b0 [
b10011 Q
b1 >
b1 c
b1 y
b1 <
b1 {
b1 )
b1 F
b1 n
1-
#210
b10100 3
0-
#215
b1000000 =
b1000000 b
b1000000 z
b0 d
0J
b1 K
b1 e
b0 X
b0 |
b111 V
b111 w
b0 U
b0 v
b1010 G
b1010 a
b1010 k
b10000111 7
b10000111 g
b100 ;
b100 j
b1 :
b1 i
b10 8
b10 h
b0 I
b0 m
b111 H
b111 l
b0 Y
b0 }
0Z
b1 [
b10001 *
b10001 6
b10001 T
b101010000111 S
b101010000111 f
b10100 Q
1-
#220
b10101 3
0-
